setup.cfg
setup.py
django_fb_oauth.egg-info/PKG-INFO
django_fb_oauth.egg-info/SOURCES.txt
django_fb_oauth.egg-info/dependency_links.txt
django_fb_oauth.egg-info/requires.txt
django_fb_oauth.egg-info/top_level.txt
fbauth/__init__.py
fbauth/api.py
fbauth/client.py
fbauth/exceptions.py
fbauth/managers.py
fbauth/models.py
fbauth/tests.py
fbauth/urls.py
fbauth/utils.py
fbauth/migrations/0001_initial.py
fbauth/migrations/__init__.py