Metadata-Version: 1.1
Name: django-fb-oauth
Version: 0.0.1.dev1
Summary: Simple facebook authentication for Django.
Home-page: https://github.com/Tuss4/django-fb-oauth
Author: TJ Soptame
Author-email: tj.soptame@gmail.com
License: MIT
Keywords: django facebook oauth
Platform: UNKNOWN
Classifier: Development Status :: 2 - Pre-Alpha
Classifier: Intended Audience :: Developers
Classifier: Topic :: Software Development :: Libraries :: Python Modules
Classifier: License :: OSI Approved :: MIT License
Classifier: Programming Language :: Python :: 2.7
Classifier: Programming Language :: Python :: 3
